{
  "data": [
    {
      "text": "业务管理",
      "icon": "&#xe63c;",
      "subset": [
        {
          "text": "贷款申请",
          "icon": "&#xe621;",
          "href": "/application"
        },
        {
          "text": "待办业务",
          "icon": "&#xe621;",
          "href": "/schedule"
        },
        {
          "text": "已办业务",
          "icon": "&#xe621;",
          "href": "/done"
        }
      ]
    },
    {
      "text": "贷后管理",
      "icon": "&#xe628;",
      "href": "",
      "subset": [
        {
          "text": "贷款催收",
          "icon": "&#xe621;",
          "href": "/urge"
        },
        {
          "text": "违约处理",
          "icon": "&#xe621;",
          "href": "/break"
        }
      ]
    },
    {
      "text": "利率管理",
      "icon": "&#xe65e;",
      "href": "",
      "subset": [
        {
          "text": "利率调整",
          "icon": "&#xe621;",
          "href": "/rate"
        }
      ]
    },
    {
      "text": "查询分析",
      "icon": "&#xe629;",
      "href": "",
      "subset": [
        {
          "text": "贷款查询",
          "icon": "&#xe621;",
          "href": "/search"
        },
        {
          "text": "统计分析",
          "icon": "&#xe621;",
          "href": "/analyse"
        }
      ]
    },
    {
      "text": "客户管理",
      "icon": "&#xe612;",
      "href": "",
      "subset": [
        {
          "text": "客户管理",
          "icon": "&#xe621;",
          "href": "/customer"
        },
        {
          "text": "黑名单管理",
          "icon": "&#xe621;",
          "href": "/blacklist"
        }
      ]
    },
    {
      "text": "系统管理",
      "icon": "&#xe620;",
      "href": "",
      "subset": [
        {
          "text": "账号管理",
          "icon": "&#xe621;",
          "href": "/account"
        },
        {
          "text": "用户管理",
          "icon": "&#xe621;",
          "href": "/user"
        },
        {
          "text": "权限管理",
          "icon": "&#xe621;",
          "href": "/authority"
        }
      ]
    }
  ]
}